musco/__init__.py
musco/pytorch/__init__.py
musco/pytorch/compressor/__init__.py
musco/pytorch/compressor/compress.py
musco/pytorch/compressor/compressor.py
musco/pytorch/compressor/decompositions/__init__.py
musco/pytorch/compressor/decompositions/cp3.py
musco/pytorch/compressor/decompositions/cp4.py
musco/pytorch/compressor/decompositions/svd_layer.py
musco/pytorch/compressor/decompositions/tucker2.py
musco/pytorch/compressor/rank_selection/__init__.py
musco/pytorch/compressor/rank_selection/estimator.py
musco/pytorch/compressor/rank_selection/vbmf.py
musco_pytorch-1.0.6.dist-info/LICENSE
musco_pytorch-1.0.6.dist-info/METADATA
musco_pytorch-1.0.6.dist-info/WHEEL
musco_pytorch-1.0.6.dist-info/top_level.txt
musco_pytorch-1.0.6.dist-info/RECORD
